README.md
setup.cfg
setup.py
d3m_metadata/__init__.py
d3m_metadata/hyperparams.py
d3m_metadata/metadata.py
d3m_metadata/params.py
d3m_metadata/problem.py
d3m_metadata/types.py
d3m_metadata/utils.py
d3m_metadata.egg-info/PKG-INFO
d3m_metadata.egg-info/SOURCES.txt
d3m_metadata.egg-info/dependency_links.txt
d3m_metadata.egg-info/requires.txt
d3m_metadata.egg-info/top_level.txt
d3m_metadata/container/__init__.py
d3m_metadata/container/dataset.py
d3m_metadata/container/list.py
d3m_metadata/container/numpy.py
d3m_metadata/container/pandas.py
d3m_metadata/schemas/v0/container.json
d3m_metadata/schemas/v0/data.json
d3m_metadata/schemas/v0/definitions.json
d3m_metadata/schemas/v0/primitive.json