Metadata-Version: 1.0
Name: d3m-metadata
Version: 2018.1.26
Summary: Metadata for values and primitives
Home-page: https://gitlab.com/datadrivendiscovery/metadata
Author: DARPA D3M Program
Author-email: UNKNOWN
License: UNKNOWN
Platform: UNKNOWN
